<ALBUM_RESPONSE>
  <NEEDS_DECISION>Y</NEEDS_DECISION>
  <RESULT_COUNT>2</RESULT_COUNT>
  <RANGE_START>1</RANGE_START>
  <RANGE_END>2</RANGE_END>
  <RANGE_TOTAL>2</RANGE_TOTAL>
  <ALBUM LANG_ID="74506" LANG="eng" SCRIPT_ID="74989" SCRIPT="latn" ORD="1">
    <FULL_RESULT>Y</FULL_RESULT>
    <GNID>191733124-5F9050D14D1CB208EB7DA5437EAC0AE1</GNID>
    <PACKAGE_LANG ID="1" LANG="eng">English</PACKAGE_LANG>
    <TITLE_OFFICIAL>
      <DISPLAY>Revolver</DISPLAY>
    </TITLE_OFFICIAL>
    <YEAR>1966</YEAR>
    <GENRE_LEVEL1>Rock</GENRE_LEVEL1>
    <LABEL>EMI</LABEL>
    <TOTAL_IN_SET>1</TOTAL_IN_SET>
    <DISC_IN_SET>1</DISC_IN_SET>
    <ARTIST>
      <NAME_OFFICIAL>
        <DISPLAY>The Beatles</DISPLAY>
        <GIVEN>Beatles</GIVEN>
        <PREFIX>The</PREFIX>
      </NAME_OFFICIAL>
      <CONTRIBUTOR>
        <GNID>191733124-5F9050D14D1CB208EB7DA5437EAC0AE1</GNID>
        <NAME_OFFICIAL>
          <DISPLAY>The Beatles</DISPLAY>
          <GIVEN>Beatles</GIVEN>
          <PREFIX>The</PREFIX>
        </NAME_OFFICIAL>
        <ORIGIN_LEVEL1>Western Europe</ORIGIN_LEVEL1>
        <ORIGIN_LEVEL2>United Kingdom</ORIGIN_LEVEL2>
        <ORIGIN_LEVEL3>England</ORIGIN_LEVEL3>
        <ORIGIN_LEVEL4>Liverpool</ORIGIN_LEVEL4>
        <ERA_LEVEL1>1960s</ERA_LEVEL1>
        <ERA_LEVEL2>1960s</ERA_LEVEL2>
        <ERA_LEVEL3>1960s</ERA_LEVEL3>
        <TYPE_LEVEL1>Male</TYPE_LEVEL1>
        <TYPE_LEVEL2>Male Group</TYPE_LEVEL2>
      </CONTRIBUTOR>
    </ARTIST>
    <TRACK_COUNT>14</TRACK_COUNT>
    <TRACK_MATCHED>7</TRACK_MATCHED>
    <TRACK ORD="1">
      <TRACK_NUM>1</TRACK_NUM>
      <GNID>191733125-A3BC07791B102B1082A3DC4D430D8FC8</GNID>
      <TITLE_OFFICIAL>
        <DISPLAY>Taxman</DISPLAY>
      </TITLE_OFFICIAL>
      <YEAR>1966</YEAR>
    </TRACK>
    <TRACK ORD="2">
      <TRACK_NUM>2</TRACK_NUM>
      <GNID>191733126-AF512C0E3A382FF50BF9660E0B0A265B</GNID>
      <TITLE_OFFICIAL>
        <DISPLAY>Eleanor Rigby</DISPLAY>
      </TITLE_OFFICIAL>
      <YEAR>1966</YEAR>
    </TRACK>
    <TRACK ORD="3">
      <TRACK_NUM>3</TRACK_NUM>
      <GNID>191733127-511B078B03360F81D9C9315320009645</GNID>
      <TITLE_OFFICIAL>
        <DISPLAY>I&apos;m Only Sleeping</DISPLAY>
      </TITLE_OFFICIAL>
      <YEAR>1966</YEAR>
    </TRACK>
    <TRACK ORD="4">
      <TRACK_NUM>4</TRACK_NUM>
      <GNID>191733128-0F069A31EBD1C798631710E7E9702B31</GNID>
      <TITLE_OFFICIAL>
        <DISPLAY>Love You To</DISPLAY>
      </TITLE_OFFICIAL>
      <YEAR>1966</YEAR>
    </TRACK>
    <TRACK ORD="5">
      <TRACK_NUM>5</TRACK_NUM>
      <GNID>191733129-58EA0B7ED283A315902769AFF97A6132</GNID>
      <TITLE_OFFICIAL>
        <DISPLAY>Here, There And Everywhere</DISPLAY>
      </TITLE_OFFICIAL>
      <YEAR>1966</YEAR>
    </TRACK>
    <TRACK ORD="6">
      <TRACK_NUM>6</TRACK_NUM>
      <GNID>191733130-6850D24676D7194FEB7F4A291D25BEB2</GNID>
      <TITLE_OFFICIAL>
        <DISPLAY>Yellow Submarine</DISPLAY>
      </TITLE_OFFICIAL>
      <YEAR>1966</YEAR>
    </TRACK>
    <TRACK ORD="7">
      <TRACK_NUM>7</TRACK_NUM>
      <MATCHED>Y</MATCHED>
      <MATCH_POSITION>33715</MATCH_POSITION>
      <MATCH_DURATION>2972</MATCH_DURATION>
      <GNID>191733131-EDFC6CEA8B01648EC1C5686367600DCD</GNID>
      <DURATION UNITS="ms">155666</DURATION>
      <TITLE_OFFICIAL>
        <DISPLAY>She Said She Said</DISPLAY>
      </TITLE_OFFICIAL>
      <YEAR>1966</YEAR>
    </TRACK>
    <TRACK ORD="8">
      <TRACK_NUM>8</TRACK_NUM>
      <GNID>191733132-AD87D5296EFA563295C7D194ABD94570</GNID>
      <TITLE_OFFICIAL>
        <DISPLAY>Good Day Sunshine</DISPLAY>
      </TITLE_OFFICIAL>
      <YEAR>1966</YEAR>
    </TRACK>
    <TRACK ORD="9">
      <TRACK_NUM>9</TRACK_NUM>
      <GNID>191733133-6DE7FBAF93FD5B2E22FAFFB0F45FD341</GNID>
      <TITLE_OFFICIAL>
        <DISPLAY>And Your Bird Can Sing</DISPLAY>
      </TITLE_OFFICIAL>
      <YEAR>1966</YEAR>
    </TRACK>
    <TRACK ORD="10">
      <TRACK_NUM>10</TRACK_NUM>
      <GNID>191733134-9A98374386ECB65E83672DEAB1B13872</GNID>
      <TITLE_OFFICIAL>
        <DISPLAY>For No One</DISPLAY>
      </TITLE_OFFICIAL>
      <YEAR>1966</YEAR>
    </TRACK>
    <TRACK ORD="11">
      <TRACK_NUM>11</TRACK_NUM>
      <GNID>191733135-5D0389B4EFC1CE8F0886C4867785DFFF</GNID>
      <TITLE_OFFICIAL>
        <DISPLAY>Doctor Robert</DISPLAY>
      </TITLE_OFFICIAL>
      <YEAR>1966</YEAR>
    </TRACK>
    <TRACK ORD="12">
      <TRACK_NUM>12</TRACK_NUM>
      <GNID>191733136-AC2AC7D955BFED3AFA01F0A0520BEA60</GNID>
      <TITLE_OFFICIAL>
        <DISPLAY>I Want To Tell You</DISPLAY>
      </TITLE_OFFICIAL>
      <YEAR>1966</YEAR>
    </TRACK>
    <TRACK ORD="13">
      <TRACK_NUM>13</TRACK_NUM>
      <GNID>191733137-2CFD94FE73DCE86A981B295E0BDDA874</GNID>
      <TITLE_OFFICIAL>
        <DISPLAY>Got To Get You Into My Life</DISPLAY>
      </TITLE_OFFICIAL>
      <YEAR>1966</YEAR>
    </TRACK>
    <TRACK ORD="14">
      <TRACK_NUM>14</TRACK_NUM>
      <GNID>191733138-F5A50F87BEA3FC904D96207AE37198B4</GNID>
      <TITLE_OFFICIAL>
        <DISPLAY>Tomorrow Never Knows</DISPLAY>
      </TITLE_OFFICIAL>
      <YEAR>1966</YEAR>
    </TRACK>
  </ALBUM>
  <ALBUM LANG_ID="74506" LANG="eng" SCRIPT_ID="74989" SCRIPT="latn" ORD="2">
    <FULL_RESULT>Y</FULL_RESULT>
    <GNID>191733109-D91D2E9DB19527C2FEF0C127A41F852E</GNID>
    <PACKAGE_LANG ID="1" LANG="eng">English</PACKAGE_LANG>
    <TITLE_OFFICIAL>
      <DISPLAY>Revolver</DISPLAY>
    </TITLE_OFFICIAL>
    <YEAR>1966</YEAR>
    <GENRE_LEVEL1>Rock</GENRE_LEVEL1>
    <LABEL>Parlophone</LABEL>
    <TOTAL_IN_SET>1</TOTAL_IN_SET>
    <DISC_IN_SET>1</DISC_IN_SET>
    <ARTIST>
      <NAME_OFFICIAL>
        <DISPLAY>The Beatles</DISPLAY>
        <GIVEN>Beatles</GIVEN>
        <PREFIX>The</PREFIX>
      </NAME_OFFICIAL>
      <CONTRIBUTOR>
        <GNID>191733109-D91D2E9DB19527C2FEF0C127A41F852E</GNID>
        <NAME_OFFICIAL>
          <DISPLAY>The Beatles</DISPLAY>
          <GIVEN>Beatles</GIVEN>
          <PREFIX>The</PREFIX>
        </NAME_OFFICIAL>
        <ORIGIN_LEVEL1>Western Europe</ORIGIN_LEVEL1>
        <ORIGIN_LEVEL2>United Kingdom</ORIGIN_LEVEL2>
        <ORIGIN_LEVEL3>England</ORIGIN_LEVEL3>
        <ORIGIN_LEVEL4>Liverpool</ORIGIN_LEVEL4>
        <ERA_LEVEL1>1960s</ERA_LEVEL1>
        <ERA_LEVEL2>1960s</ERA_LEVEL2>
        <ERA_LEVEL3>1960s</ERA_LEVEL3>
        <TYPE_LEVEL1>Male</TYPE_LEVEL1>
        <TYPE_LEVEL2>Male Group</TYPE_LEVEL2>
      </CONTRIBUTOR>
    </ARTIST>
    <TRACK_COUNT>14</TRACK_COUNT>
    <TRACK_MATCHED>7</TRACK_MATCHED>
    <TRACK ORD="1">
      <TRACK_NUM>1</TRACK_NUM>
      <GNID>191733110-2E40F6BCD259AC02399FCDE19C6FEFA5</GNID>
      <TITLE_OFFICIAL>
        <DISPLAY>Taxman</DISPLAY>
      </TITLE_OFFICIAL>
      <YEAR>1966</YEAR>
    </TRACK>
    <TRACK ORD="2">
      <TRACK_NUM>2</TRACK_NUM>
      <GNID>191733111-F933184116FB824D706EA24113F9300B</GNID>
      <TITLE_OFFICIAL>
        <DISPLAY>Eleanor Rigby</DISPLAY>
      </TITLE_OFFICIAL>
      <YEAR>1966</YEAR>
    </TRACK>
    <TRACK ORD="3">
      <TRACK_NUM>3</TRACK_NUM>
      <GNID>191733112-757C637A1668D09D14335238F4ACD9B0</GNID>
      <TITLE_OFFICIAL>
        <DISPLAY>I&apos;m Only Sleeping</DISPLAY>
      </TITLE_OFFICIAL>
      <YEAR>1966</YEAR>
    </TRACK>
    <TRACK ORD="4">
      <TRACK_NUM>4</TRACK_NUM>
      <GNID>191733113-857A0E7CDFE33E319A141EEB25D0BDBB</GNID>
      <TITLE_OFFICIAL>
        <DISPLAY>Love You To</DISPLAY>
      </TITLE_OFFICIAL>
      <YEAR>1966</YEAR>
    </TRACK>
    <TRACK ORD="5">
      <TRACK_NUM>5</TRACK_NUM>
      <GNID>191733114-E43434CB13738934169D4B2EE67E41DD</GNID>
      <TITLE_OFFICIAL>
        <DISPLAY>Here, There And Everywhere</DISPLAY>
      </TITLE_OFFICIAL>
      <YEAR>1966</YEAR>
    </TRACK>
    <TRACK ORD="6">
      <TRACK_NUM>6</TRACK_NUM>
      <GNID>191733115-703EB8F6477C14D5DD532758E2494073</GNID>
      <TITLE_OFFICIAL>
        <DISPLAY>Yellow Submarine</DISPLAY>
      </TITLE_OFFICIAL>
      <YEAR>1966</YEAR>
    </TRACK>
    <TRACK ORD="7">
      <TRACK_NUM>7</TRACK_NUM>
      <MATCHED>Y</MATCHED>
      <MATCH_POSITION>33715</MATCH_POSITION>
      <MATCH_DURATION>2972</MATCH_DURATION>
      <GNID>191733116-3AA7567BC7DA1BAEDAB0E56499205F0E</GNID>
      <DURATION UNITS="ms">158870</DURATION>
      <TITLE_OFFICIAL>
        <DISPLAY>She Said She Said</DISPLAY>
      </TITLE_OFFICIAL>
      <YEAR>1966</YEAR>
    </TRACK>
    <TRACK ORD="8">
      <TRACK_NUM>8</TRACK_NUM>
      <GNID>191733117-022D621A2BC86A961E96A608F081155B</GNID>
      <TITLE_OFFICIAL>
        <DISPLAY>Good Day Sunshine</DISPLAY>
      </TITLE_OFFICIAL>
      <YEAR>1966</YEAR>
    </TRACK>
    <TRACK ORD="9">
      <TRACK_NUM>9</TRACK_NUM>
      <GNID>191733118-CBD74B1AC48B07D862AB366630C5F520</GNID>
      <TITLE_OFFICIAL>
        <DISPLAY>And Your Bird Can Sing</DISPLAY>
      </TITLE_OFFICIAL>
      <YEAR>1966</YEAR>
    </TRACK>
    <TRACK ORD="10">
      <TRACK_NUM>10</TRACK_NUM>
      <GNID>191733119-CAA345EA7DACCEE48ECC6911D80EA591</GNID>
      <TITLE_OFFICIAL>
        <DISPLAY>For No One</DISPLAY>
      </TITLE_OFFICIAL>
      <YEAR>1966</YEAR>
    </TRACK>
    <TRACK ORD="11">
      <TRACK_NUM>11</TRACK_NUM>
      <GNID>191733120-F5414F8F5B2FFA85BF01F28915C94D3A</GNID>
      <TITLE_OFFICIAL>
        <DISPLAY>Doctor Robert</DISPLAY>
      </TITLE_OFFICIAL>
      <YEAR>1966</YEAR>
    </TRACK>
    <TRACK ORD="12">
      <TRACK_NUM>12</TRACK_NUM>
      <GNID>191733121-D3BCFBBA8CEDA973E10CD173FC8A3564</GNID>
      <TITLE_OFFICIAL>
        <DISPLAY>I Want To Tell You</DISPLAY>
      </TITLE_OFFICIAL>
      <YEAR>1966</YEAR>
    </TRACK>
    <TRACK ORD="13">
      <TRACK_NUM>13</TRACK_NUM>
      <GNID>191733122-C93737302E3DCF8B2516B0493A9531A3</GNID>
      <TITLE_OFFICIAL>
        <DISPLAY>Got To Get You Into My Life</DISPLAY>
      </TITLE_OFFICIAL>
      <YEAR>1966</YEAR>
    </TRACK>
    <TRACK ORD="14">
      <TRACK_NUM>14</TRACK_NUM>
      <GNID>191733123-07ED56391A6A9057945BC7774C33C3FD</GNID>
      <TITLE_OFFICIAL>
        <DISPLAY>Tomorrow Never Knows</DISPLAY>
      </TITLE_OFFICIAL>
      <YEAR>1966</YEAR>
    </TRACK>
  </ALBUM>
</ALBUM_RESPONSE>
